[{"seg_id":"seg_0137_6768","video_id":"jXZrO2pcIEw","video_url":"https://youtu.be/jXZrO2pcIEw","t_start":225.6,"t_end":226.3,"duration":0.7,"spotter_score":0.814,"energy_peak":0.443},{"seg_id":"seg_0139_6811","video_id":"jXZrO2pcIEw","video_url":"https://youtu.be/jXZrO2pcIEw","t_start":227.033,"t_end":227.767,"duration":0.733,"spotter_score":0.517,"energy_peak":0.588},{"seg_id":"seg_0140_7097","video_id":"jXZrO2pcIEw","video_url":"https://youtu.be/jXZrO2pcIEw","t_start":236.567,"t_end":236.933,"duration":0.367,"spotter_score":0.506,"energy_peak":0.27},{"seg_id":"seg_0141_7119","video_id":"jXZrO2pcIEw","video_url":"https://youtu.be/jXZrO2pcIEw","t_start":237.3,"t_end":237.8,"duration":0.5,"spotter_score":0.833,"energy_peak":0.557},{"seg_id":"seg_0144_7188","video_id":"jXZrO2pcIEw","video_url":"https://youtu.be/jXZrO2pcIEw","t_start":239.6,"t_end":240.0,"duration":0.4,"spotter_score":0.627,"energy_peak":0.306},{"seg_id":"seg_0145_7273","video_id":"jXZrO2pcIEw","video_url":"https://youtu.be/jXZrO2pcIEw","t_start":242.433,"t_end":242.867,"duration":0.433,"spotter_score":0.931,"energy_peak":0.567},{"seg_id":"seg_0147_7296","video_id":"jXZrO2pcIEw","video_url":"https://youtu.be/jXZrO2pcIEw","t_start":243.2,"t_end":244.167,"duration":0.967,"spotter_score":0.64,"energy_peak":0.423},{"seg_id":"seg_0148_7376","video_id":"jXZrO2pcIEw","video_url":"https://youtu.be/jXZrO2pcIEw","t_start":245.867,"t_end":246.867,"duration":1.0,"spotter_score":0.603,"energy_peak":0.459},{"seg_id":"seg_0149_7486","video_id":"jXZrO2pcIEw","video_url":"https://youtu.be/jXZrO2pcIEw","t_start":249.533,"t_end":250.0,"duration":0.467,"spotter_score":0.831,"energy_peak":0.661},{"seg_id":"seg_0152_7619","video_id":"jXZrO2pcIEw","video_url":"https://youtu.be/jXZrO2pcIEw","t_start":253.967,"t_end":254.3,"duration":0.333,"spotter_score":0.529,"energy_peak":0.332},{"seg_id":"seg_0153_7681","video_id":"jXZrO2pcIEw","video_url":"https://youtu.be/jXZrO2pcIEw","t_start":256.033,"t_end":256.367,"duration":0.333,"spotter_score":0.787,"energy_peak":0.381},{"seg_id":"seg_0160_7890","video_id":"jXZrO2pcIEw","video_url":"https://youtu.be/jXZrO2pcIEw","t_start":263.0,"t_end":263.933,"duration":0.933,"spotter_score":0.78,"energy_peak":0.359},{"seg_id":"seg_0161_8041","video_id":"jXZrO2pcIEw","video_url":"https://youtu.be/jXZrO2pcIEw","t_start":268.033,"t_end":268.733,"duration":0.7,"spotter_score":0.861,"energy_peak":0.718},{"seg_id":"seg_0162_8056","video_id":"jXZrO2pcIEw","video_url":"https://youtu.be/jXZrO2pcIEw","t_start":268.533,"t_end":269.267,"duration":0.733,"spotter_score":0.877,"energy_peak":0.509},{"seg_id":"seg_0164_8127","video_id":"jXZrO2pcIEw","video_url":"https://youtu.be/jXZrO2pcIEw","t_start":270.9,"t_end":271.5,"duration":0.6,"spotter_score":0.586,"energy_peak":0.314},{"seg_id":"seg_0002_196","video_id":"JzDXRkIGQt4","video_url":"https://youtu.be/JzDXRkIGQt4","t_start":6.533,"t_end":6.967,"duration":0.433,"spotter_score":0.967,"energy_peak":0.733},{"seg_id":"seg_0006_315","video_id":"JzDXRkIGQt4","video_url":"https://youtu.be/JzDXRkIGQt4","t_start":10.5,"t_end":11.567,"duration":1.067,"spotter_score":0.877,"energy_peak":0.398},{"seg_id":"seg_0008_393","video_id":"JzDXRkIGQt4","video_url":"https://youtu.be/JzDXRkIGQt4","t_start":13.1,"t_end":14.033,"duration":0.933,"spotter_score":0.578,"energy_peak":0.412},{"seg_id":"seg_0010_431","video_id":"JzDXRkIGQt4","video_url":"https://youtu.be/JzDXRkIGQt4","t_start":14.367,"t_end":14.733,"duration":0.367,"spotter_score":0.978,"energy_peak":0.909},{"seg_id":"seg_0011_465","video_id":"JzDXRkIGQt4","video_url":"https://youtu.be/JzDXRkIGQt4","t_start":15.5,"t_end":15.833,"duration":0.333,"spotter_score":0.953,"energy_peak":0.291},{"seg_id":"seg_0012_521","video_id":"JzDXRkIGQt4","video_url":"https://youtu.be/JzDXRkIGQt4","t_start":17.367,"t_end":18.1,"duration":0.733,"spotter_score":0.925,"energy_peak":0.439},{"seg_id":"seg_0013_558","video_id":"JzDXRkIGQt4","video_url":"https://youtu.be/JzDXRkIGQt4","t_start":18.6,"t_end":19.367,"duration":0.767,"spotter_score":0.937,"energy_peak":0.541},{"seg_id":"seg_0014_587","video_id":"JzDXRkIGQt4","video_url":"https://youtu.be/JzDXRkIGQt4","t_start":19.567,"t_end":20.267,"duration":0.7,"spotter_score":0.97,"energy_peak":0.735},{"seg_id":"seg_0015_604","video_id":"JzDXRkIGQt4","video_url":"https://youtu.be/JzDXRkIGQt4","t_start":20.133,"t_end":20.933,"duration":0.8,"spotter_score":0.661,"energy_peak":0.39},{"seg_id":"seg_0016_660","video_id":"JzDXRkIGQt4","video_url":"https://youtu.be/JzDXRkIGQt4","t_start":22.0,"t_end":23.067,"duration":1.067,"spotter_score":0.787,"energy_peak":0.523},{"seg_id":"seg_0018_683","video_id":"JzDXRkIGQt4","video_url":"https://youtu.be/JzDXRkIGQt4","t_start":22.767,"t_end":23.6,"duration":0.833,"spotter_score":0.971,"energy_peak":0.487},{"seg_id":"seg_0019_730","video_id":"JzDXRkIGQt4","video_url":"https://youtu.be/JzDXRkIGQt4","t_start":24.333,"t_end":25.367,"duration":1.033,"spotter_score":0.884,"energy_peak":0.491},{"seg_id":"seg_0020_763","video_id":"JzDXRkIGQt4","video_url":"https://youtu.be/JzDXRkIGQt4","t_start":25.433,"t_end":26.2,"duration":0.767,"spotter_score":0.957,"energy_peak":0.487},{"seg_id":"seg_0021_804","video_id":"JzDXRkIGQt4","video_url":"https://youtu.be/JzDXRkIGQt4","t_start":26.8,"t_end":27.667,"duration":0.867,"spotter_score":0.938,"energy_peak":0.674},{"seg_id":"seg_0022_822","video_id":"JzDXRkIGQt4","video_url":"https://youtu.be/JzDXRkIGQt4","t_start":27.4,"t_end":28.167,"duration":0.767,"spotter_score":0.922,"energy_peak":0.666},{"seg_id":"seg_0023_866","video_id":"JzDXRkIGQt4","video_url":"https://youtu.be/JzDXRkIGQt4","t_start":28.867,"t_end":29.4,"duration":0.533,"spotter_score":0.986,"energy_peak":0.643},{"seg_id":"seg_0024_876","video_id":"JzDXRkIGQt4","video_url":"https://youtu.be/JzDXRkIGQt4","t_start":29.2,"t_end":29.9,"duration":0.7,"spotter_score":0.573,"energy_peak":0.327},{"seg_id":"seg_0025_918","video_id":"JzDXRkIGQt4","video_url":"https://youtu.be/JzDXRkIGQt4","t_start":30.6,"t_end":31.433,"duration":0.833,"spotter_score":0.742,"energy_peak":0.399},{"seg_id":"seg_0027_980","video_id":"JzDXRkIGQt4","video_url":"https://youtu.be/JzDXRkIGQt4","t_start":32.667,"t_end":33.433,"duration":0.767,"spotter_score":0.956,"energy_peak":0.644},{"seg_id":"seg_0028_1008","video_id":"JzDXRkIGQt4","video_url":"https://youtu.be/JzDXRkIGQt4","t_start":33.6,"t_end":33.867,"duration":0.267,"spotter_score":0.888,"energy_peak":0.276},{"seg_id":"seg_0029_1021","video_id":"JzDXRkIGQt4","video_url":"https://youtu.be/JzDXRkIGQt4","t_start":34.033,"t_end":34.367,"duration":0.333,"spotter_score":0.687,"energy_peak":0.358},{"seg_id":"seg_0030_1053","video_id":"JzDXRkIGQt4","video_url":"https://youtu.be/JzDXRkIGQt4","t_start":35.1,"t_end":36.0,"duration":0.9,"spotter_score":0.75,"energy_peak":0.587},{"seg_id":"seg_0031_1118","video_id":"JzDXRkIGQt4","video_url":"https://youtu.be/JzDXRkIGQt4","t_start":37.267,"t_end":38.0,"duration":0.733,"spotter_score":0.609,"energy_peak":0.675},{"seg_id":"seg_0033_1211","video_id":"JzDXRkIGQt4","video_url":"https://youtu.be/JzDXRkIGQt4","t_start":40.367,"t_end":40.767,"duration":0.4,"spotter_score":0.516,"energy_peak":0.485},{"seg_id":"seg_0034_1260","video_id":"JzDXRkIGQt4","video_url":"https://youtu.be/JzDXRkIGQt4","t_start":42.0,"t_end":42.4,"duration":0.4,"spotter_score":0.98,"energy_peak":0.492},{"seg_id":"seg_0035_1334","video_id":"JzDXRkIGQt4","video_url":"https://youtu.be/JzDXRkIGQt4","t_start":44.467,"t_end":44.8,"duration":0.333,"spotter_score":0.99,"energy_peak":0.371},{"seg_id":"seg_0036_1356","video_id":"JzDXRkIGQt4","video_url":"https://youtu.be/JzDXRkIGQt4","t_start":45.2,"t_end":45.467,"duration":0.267,"spotter_score":0.982,"energy_peak":0.319},{"seg_id":"seg_0037_1381","video_id":"JzDXRkIGQt4","video_url":"https://youtu.be/JzDXRkIGQt4","t_start":46.033,"t_end":46.333,"duration":0.3,"spotter_score":0.975,"energy_peak":0.452},{"seg_id":"seg_0038_1421","video_id":"JzDXRkIGQt4","video_url":"https://youtu.be/JzDXRkIGQt4","t_start":47.367,"t_end":47.733,"duration":0.367,"spotter_score":0.991,"energy_peak":0.478},{"seg_id":"seg_0039_1448","video_id":"JzDXRkIGQt4","video_url":"https://youtu.be/JzDXRkIGQt4","t_start":48.267,"t_end":48.767,"duration":0.5,"spotter_score":0.928,"energy_peak":0.466},{"seg_id":"seg_0040_1499","video_id":"JzDXRkIGQt4","video_url":"https://youtu.be/JzDXRkIGQt4","t_start":49.967,"t_end":50.567,"duration":0.6,"spotter_score":0.859,"energy_peak":0.436},{"seg_id":"seg_0041_1536","video_id":"JzDXRkIGQt4","video_url":"https://youtu.be/JzDXRkIGQt4","t_start":51.2,"t_end":51.633,"duration":0.433,"spotter_score":0.92,"energy_peak":0.911},{"seg_id":"seg_0042_1554","video_id":"JzDXRkIGQt4","video_url":"https://youtu.be/JzDXRkIGQt4","t_start":51.8,"t_end":52.233,"duration":0.433,"spotter_score":0.882,"energy_peak":0.482},{"seg_id":"seg_0043_1563","video_id":"JzDXRkIGQt4","video_url":"https://youtu.be/JzDXRkIGQt4","t_start":52.1,"t_end":52.767,"duration":0.667,"spotter_score":0.638,"energy_peak":0.372},{"seg_id":"seg_0044_1596","video_id":"JzDXRkIGQt4","video_url":"https://youtu.be/JzDXRkIGQt4","t_start":53.2,"t_end":53.767,"duration":0.567,"spotter_score":0.97,"energy_peak":0.377},{"seg_id":"seg_0045_1627","video_id":"JzDXRkIGQt4","video_url":"https://youtu.be/JzDXRkIGQt4","t_start":54.233,"t_end":54.833,"duration":0.6,"spotter_score":0.92,"energy_peak":0.586},{"seg_id":"seg_0046_1672","video_id":"JzDXRkIGQt4","video_url":"https://youtu.be/JzDXRkIGQt4","t_start":55.733,"t_end":56.133,"duration":0.4,"spotter_score":0.924,"energy_peak":0.507},{"seg_id":"seg_0047_1693","video_id":"JzDXRkIGQt4","video_url":"https://youtu.be/JzDXRkIGQt4","t_start":56.433,"t_end":56.867,"duration":0.433,"spotter_score":0.724,"energy_peak":0.299},{"seg_id":"seg_0048_1715","video_id":"JzDXRkIGQt4","video_url":"https://youtu.be/JzDXRkIGQt4","t_start":57.167,"t_end":57.533,"duration":0.367,"spotter_score":0.94,"energy_peak":0.615},{"seg_id":"seg_0049_1746","video_id":"JzDXRkIGQt4","video_url":"https://youtu.be/JzDXRkIGQt4","t_start":58.2,"t_end":58.8,"duration":0.6,"spotter_score":0.931,"energy_peak":0.736},{"seg_id":"seg_0052_1843","video_id":"JzDXRkIGQt4","video_url":"https://youtu.be/JzDXRkIGQt4","t_start":61.433,"t_end":61.933,"duration":0.5,"spotter_score":0.994,"energy_peak":0.387},{"seg_id":"seg_0055_1903","video_id":"JzDXRkIGQt4","video_url":"https://youtu.be/JzDXRkIGQt4","t_start":63.433,"t_end":64.5,"duration":1.067,"spotter_score":0.849,"energy_peak":0.341},{"seg_id":"seg_0056_1936","video_id":"JzDXRkIGQt4","video_url":"https://youtu.be/JzDXRkIGQt4","t_start":64.533,"t_end":65.0,"duration":0.467,"spotter_score":0.957,"energy_peak":0.682},{"seg_id":"seg_0057_2010","video_id":"JzDXRkIGQt4","video_url":"https://youtu.be/JzDXRkIGQt4","t_start":67.0,"t_end":67.9,"duration":0.9,"spotter_score":0.765,"energy_peak":0.514},{"seg_id":"seg_0058_2036","video_id":"JzDXRkIGQt4","video_url":"https://youtu.be/JzDXRkIGQt4","t_start":67.867,"t_end":68.933,"duration":1.067,"spotter_score":0.911,"energy_peak":0.477},{"seg_id":"seg_0060_2081","video_id":"JzDXRkIGQt4","video_url":"https://youtu.be/JzDXRkIGQt4","t_start":69.367,"t_end":69.9,"duration":0.533,"spotter_score":0.943,"energy_peak":0.98},{"seg_id":"seg_0061_2120","video_id":"JzDXRkIGQt4","video_url":"https://youtu.be/JzDXRkIGQt4","t_start":70.667,"t_end":71.233,"duration":0.567,"spotter_score":0.796,"energy_peak":0.677},{"seg_id":"seg_0062_2156","video_id":"JzDXRkIGQt4","video_url":"https://youtu.be/JzDXRkIGQt4","t_start":71.867,"t_end":72.4,"duration":0.533,"spotter_score":0.928,"energy_peak":0.431},{"seg_id":"seg_0063_2177","video_id":"JzDXRkIGQt4","video_url":"https://youtu.be/JzDXRkIGQt4","t_start":72.567,"t_end":72.9,"duration":0.333,"spotter_score":0.903,"energy_peak":0.66},{"seg_id":"seg_0064_2198","video_id":"JzDXRkIGQt4","video_url":"https://youtu.be/JzDXRkIGQt4","t_start":73.267,"t_end":73.733,"duration":0.467,"spotter_score":0.975,"energy_peak":0.613},{"seg_id":"seg_0065_2224","video_id":"JzDXRkIGQt4","video_url":"https://youtu.be/JzDXRkIGQt4","t_start":74.133,"t_end":74.7,"duration":0.567,"spotter_score":0.953,"energy_peak":0.792},{"seg_id":"seg_0066_2296","video_id":"JzDXRkIGQt4","video_url":"https://youtu.be/JzDXRkIGQt4","t_start":76.533,"t_end":76.933,"duration":0.4,"spotter_score":0.989,"energy_peak":0.757},{"seg_id":"seg_0067_2326","video_id":"JzDXRkIGQt4","video_url":"https://youtu.be/JzDXRkIGQt4","t_start":77.533,"t_end":78.067,"duration":0.533,"spotter_score":0.854,"energy_peak":0.438},{"seg_id":"seg_0068_2347","video_id":"JzDXRkIGQt4","video_url":"https://youtu.be/JzDXRkIGQt4","t_start":78.233,"t_end":78.633,"duration":0.4,"spotter_score":0.993,"energy_peak":1.0},{"seg_id":"seg_0069_2423","video_id":"JzDXRkIGQt4","video_url":"https://youtu.be/JzDXRkIGQt4","t_start":80.767,"t_end":81.3,"duration":0.533,"spotter_score":0.961,"energy_peak":0.531},{"seg_id":"seg_0070_2462","video_id":"JzDXRkIGQt4","video_url":"https://youtu.be/JzDXRkIGQt4","t_start":82.067,"t_end":82.367,"duration":0.3,"spotter_score":0.978,"energy_peak":0.584},{"seg_id":"seg_0071_2475","video_id":"JzDXRkIGQt4","video_url":"https://youtu.be/JzDXRkIGQt4","t_start":82.5,"t_end":82.967,"duration":0.467,"spotter_score":0.974,"energy_peak":0.384},{"seg_id":"seg_0072_2502","video_id":"JzDXRkIGQt4","video_url":"https://youtu.be/JzDXRkIGQt4","t_start":83.4,"t_end":84.0,"duration":0.6,"spotter_score":0.967,"energy_peak":0.658},{"seg_id":"seg_0073_2584","video_id":"JzDXRkIGQt4","video_url":"https://youtu.be/JzDXRkIGQt4","t_start":86.133,"t_end":86.933,"duration":0.8,"spotter_score":0.969,"energy_peak":0.415},{"seg_id":"seg_0075_2647","video_id":"JzDXRkIGQt4","video_url":"https://youtu.be/JzDXRkIGQt4","t_start":88.233,"t_end":89.167,"duration":0.933,"spotter_score":0.896,"energy_peak":0.323},{"seg_id":"seg_0076_2664","video_id":"JzDXRkIGQt4","video_url":"https://youtu.be/JzDXRkIGQt4","t_start":88.8,"t_end":89.6,"duration":0.8,"spotter_score":0.837,"energy_peak":0.635},{"seg_id":"seg_0077_2693","video_id":"JzDXRkIGQt4","video_url":"https://youtu.be/JzDXRkIGQt4","t_start":89.767,"t_end":90.433,"duration":0.667,"spotter_score":0.78,"energy_peak":0.564},{"seg_id":"seg_0080_2756","video_id":"JzDXRkIGQt4","video_url":"https://youtu.be/JzDXRkIGQt4","t_start":91.867,"t_end":92.933,"duration":1.067,"spotter_score":0.947,"energy_peak":0.553},{"seg_id":"seg_0082_2793","video_id":"JzDXRkIGQt4","video_url":"https://youtu.be/JzDXRkIGQt4","t_start":93.1,"t_end":93.533,"duration":0.433,"spotter_score":0.933,"energy_peak":0.367},{"seg_id":"seg_0084_2826","video_id":"JzDXRkIGQt4","video_url":"https://youtu.be/JzDXRkIGQt4","t_start":94.2,"t_end":94.633,"duration":0.433,"spotter_score":0.957,"energy_peak":0.518},{"seg_id":"seg_0085_2851","video_id":"JzDXRkIGQt4","video_url":"https://youtu.be/JzDXRkIGQt4","t_start":95.033,"t_end":95.333,"duration":0.3,"spotter_score":0.895,"energy_peak":0.29},{"seg_id":"seg_0086_2899","video_id":"JzDXRkIGQt4","video_url":"https://youtu.be/JzDXRkIGQt4","t_start":96.633,"t_end":97.333,"duration":0.7,"spotter_score":0.936,"energy_peak":0.467},{"seg_id":"seg_0087_2939","video_id":"JzDXRkIGQt4","video_url":"https://youtu.be/JzDXRkIGQt4","t_start":97.967,"t_end":98.933,"duration":0.967,"spotter_score":0.74,"energy_peak":0.573},{"seg_id":"seg_0089_2960","video_id":"JzDXRkIGQt4","video_url":"https://youtu.be/JzDXRkIGQt4","t_start":98.667,"t_end":99.367,"duration":0.7,"spotter_score":0.814,"energy_peak":0.294},{"seg_id":"seg_0090_3012","video_id":"JzDXRkIGQt4","video_url":"https://youtu.be/JzDXRkIGQt4","t_start":100.4,"t_end":100.733,"duration":0.333,"spotter_score":0.975,"energy_peak":0.492},{"seg_id":"seg_0091_3034","video_id":"JzDXRkIGQt4","video_url":"https://youtu.be/JzDXRkIGQt4","t_start":101.133,"t_end":101.567,"duration":0.433,"spotter_score":0.957,"energy_peak":0.557},{"seg_id":"seg_0092_3089","video_id":"JzDXRkIGQt4","video_url":"https://youtu.be/JzDXRkIGQt4","t_start":102.967,"t_end":103.767,"duration":0.8,"spotter_score":0.963,"energy_peak":0.491},{"seg_id":"seg_0093_3126","video_id":"JzDXRkIGQt4","video_url":"https://youtu.be/JzDXRkIGQt4","t_start":104.2,"t_end":104.767,"duration":0.567,"spotter_score":0.645,"energy_peak":0.622},{"seg_id":"seg_0094_3156","video_id":"JzDXRkIGQt4","video_url":"https://youtu.be/JzDXRkIGQt4","t_start":105.2,"t_end":105.633,"duration":0.433,"spotter_score":0.986,"energy_peak":0.734},{"seg_id":"seg_0095_3227","video_id":"JzDXRkIGQt4","video_url":"https://youtu.be/JzDXRkIGQt4","t_start":107.567,"t_end":108.5,"duration":0.933,"spotter_score":0.954,"energy_peak":0.363},{"seg_id":"seg_0096_3265","video_id":"JzDXRkIGQt4","video_url":"https://youtu.be/JzDXRkIGQt4","t_start":108.833,"t_end":109.767,"duration":0.933,"spotter_score":0.905,"energy_peak":0.463},{"seg_id":"seg_0097_3295","video_id":"JzDXRkIGQt4","video_url":"https://youtu.be/JzDXRkIGQt4","t_start":109.833,"t_end":110.833,"duration":1.0,"spotter_score":0.926,"energy_peak":0.559},{"seg_id":"seg_0099_3330","video_id":"JzDXRkIGQt4","video_url":"https://youtu.be/JzDXRkIGQt4","t_start":111.0,"t_end":111.733,"duration":0.733,"spotter_score":0.684,"energy_peak":0.448},{"seg_id":"seg_0100_3372","video_id":"JzDXRkIGQt4","video_url":"https://youtu.be/JzDXRkIGQt4","t_start":112.4,"t_end":112.967,"duration":0.567,"spotter_score":0.938,"energy_peak":0.764},{"seg_id":"seg_0102_3421","video_id":"JzDXRkIGQt4","video_url":"https://youtu.be/JzDXRkIGQt4","t_start":114.033,"t_end":114.8,"duration":0.767,"spotter_score":0.834,"energy_peak":0.591},{"seg_id":"seg_0103_3486","video_id":"JzDXRkIGQt4","video_url":"https://youtu.be/JzDXRkIGQt4","t_start":116.2,"t_end":116.533,"duration":0.333,"spotter_score":0.988,"energy_peak":0.58},{"seg_id":"seg_0104_3507","video_id":"JzDXRkIGQt4","video_url":"https://youtu.be/JzDXRkIGQt4","t_start":116.9,"t_end":117.233,"duration":0.333,"spotter_score":0.987,"energy_peak":0.583},{"seg_id":"seg_0105_3582","video_id":"JzDXRkIGQt4","video_url":"https://youtu.be/JzDXRkIGQt4","t_start":119.4,"t_end":119.833,"duration":0.433,"spotter_score":0.973,"energy_peak":0.614},{"seg_id":"seg_0106_3594","video_id":"JzDXRkIGQt4","video_url":"https://youtu.be/JzDXRkIGQt4","t_start":119.8,"t_end":120.867,"duration":1.067,"spotter_score":0.695,"energy_peak":0.336},{"seg_id":"seg_0107_3618","video_id":"JzDXRkIGQt4","video_url":"https://youtu.be/JzDXRkIGQt4","t_start":120.6,"t_end":121.267,"duration":0.667,"spotter_score":0.964,"energy_peak":0.65},{"seg_id":"seg_0108_3645","video_id":"JzDXRkIGQt4","video_url":"https://youtu.be/JzDXRkIGQt4","t_start":121.5,"t_end":121.833,"duration":0.333,"spotter_score":0.841,"energy_peak":0.322},{"seg_id":"seg_0109_3677","video_id":"JzDXRkIGQt4","video_url":"https://youtu.be/JzDXRkIGQt4","t_start":122.567,"t_end":123.5,"duration":0.933,"spotter_score":0.959,"energy_peak":0.667},{"seg_id":"seg_0110_3701","video_id":"JzDXRkIGQt4","video_url":"https://youtu.be/JzDXRkIGQt4","t_start":123.367,"t_end":124.033,"duration":0.667,"spotter_score":0.754,"energy_peak":0.358},{"seg_id":"seg_0112_3743","video_id":"JzDXRkIGQt4","video_url":"https://youtu.be/JzDXRkIGQt4","t_start":124.767,"t_end":125.833,"duration":1.067,"spotter_score":0.835,"energy_peak":0.42},{"seg_id":"seg_0114_3799","video_id":"JzDXRkIGQt4","video_url":"https://youtu.be/JzDXRkIGQt4","t_start":126.633,"t_end":127.7,"duration":1.067,"spotter_score":0.883,"energy_peak":0.397},{"seg_id":"seg_0116_3853","video_id":"JzDXRkIGQt4","video_url":"https://youtu.be/JzDXRkIGQt4","t_start":128.433,"t_end":129.267,"duration":0.833,"spotter_score":0.91,"energy_peak":0.474},{"seg_id":"seg_0117_3900","video_id":"JzDXRkIGQt4","video_url":"https://youtu.be/JzDXRkIGQt4","t_start":130.0,"t_end":130.333,"duration":0.333,"spotter_score":0.969,"energy_peak":0.358},{"seg_id":"seg_0120_3971","video_id":"JzDXRkIGQt4","video_url":"https://youtu.be/JzDXRkIGQt4","t_start":132.367,"t_end":133.1,"duration":0.733,"spotter_score":0.54,"energy_peak":0.543},{"seg_id":"seg_0121_3988","video_id":"JzDXRkIGQt4","video_url":"https://youtu.be/JzDXRkIGQt4","t_start":132.933,"t_end":134.0,"duration":1.067,"spotter_score":0.934,"energy_peak":0.337},{"seg_id":"seg_0122_4019","video_id":"JzDXRkIGQt4","video_url":"https://youtu.be/JzDXRkIGQt4","t_start":133.967,"t_end":134.633,"duration":0.667,"spotter_score":0.949,"energy_peak":0.732},{"seg_id":"seg_0123_4063","video_id":"JzDXRkIGQt4","video_url":"https://youtu.be/JzDXRkIGQt4","t_start":135.433,"t_end":135.7,"duration":0.267,"spotter_score":0.656,"energy_peak":0.278},{"seg_id":"seg_0124_4102","video_id":"JzDXRkIGQt4","video_url":"https://youtu.be/JzDXRkIGQt4","t_start":136.733,"t_end":137.533,"duration":0.8,"spotter_score":0.593,"energy_peak":0.359},{"seg_id":"seg_0126_4156","video_id":"JzDXRkIGQt4","video_url":"https://youtu.be/JzDXRkIGQt4","t_start":138.533,"t_end":138.967,"duration":0.433,"spotter_score":0.988,"energy_peak":0.707},{"seg_id":"seg_0127_4180","video_id":"JzDXRkIGQt4","video_url":"https://youtu.be/JzDXRkIGQt4","t_start":139.333,"t_end":140.0,"duration":0.667,"spotter_score":0.945,"energy_peak":0.491},{"seg_id":"seg_0128_4256","video_id":"JzDXRkIGQt4","video_url":"https://youtu.be/JzDXRkIGQt4","t_start":141.867,"t_end":142.7,"duration":0.833,"spotter_score":0.924,"energy_peak":0.504},{"seg_id":"seg_0131_4313","video_id":"JzDXRkIGQt4","video_url":"https://youtu.be/JzDXRkIGQt4","t_start":143.767,"t_end":144.3,"duration":0.533,"spotter_score":0.972,"energy_peak":0.309},{"seg_id":"seg_0132_4338","video_id":"JzDXRkIGQt4","video_url":"https://youtu.be/JzDXRkIGQt4","t_start":144.6,"t_end":145.167,"duration":0.567,"spotter_score":0.98,"energy_peak":0.652},{"seg_id":"seg_0133_4360","video_id":"JzDXRkIGQt4","video_url":"https://youtu.be/JzDXRkIGQt4","t_start":145.333,"t_end":146.133,"duration":0.8,"spotter_score":0.789,"energy_peak":0.862},{"seg_id":"seg_0134_4377","video_id":"JzDXRkIGQt4","video_url":"https://youtu.be/JzDXRkIGQt4","t_start":145.9,"t_end":146.6,"duration":0.7,"spotter_score":0.663,"energy_peak":0.636},{"seg_id":"seg_0135_4412","video_id":"JzDXRkIGQt4","video_url":"https://youtu.be/JzDXRkIGQt4","t_start":147.067,"t_end":147.767,"duration":0.7,"spotter_score":0.965,"energy_peak":0.494},{"seg_id":"seg_0136_4458","video_id":"JzDXRkIGQt4","video_url":"https://youtu.be/JzDXRkIGQt4","t_start":148.6,"t_end":149.1,"duration":0.5,"spotter_score":0.976,"energy_peak":0.326},{"seg_id":"seg_0138_4484","video_id":"JzDXRkIGQt4","video_url":"https://youtu.be/JzDXRkIGQt4","t_start":149.467,"t_end":150.167,"duration":0.7,"spotter_score":0.963,"energy_peak":0.719},{"seg_id":"seg_0139_4533","video_id":"JzDXRkIGQt4","video_url":"https://youtu.be/JzDXRkIGQt4","t_start":151.1,"t_end":151.433,"duration":0.333,"spotter_score":0.885,"energy_peak":0.492},{"seg_id":"seg_0141_4557","video_id":"JzDXRkIGQt4","video_url":"https://youtu.be/JzDXRkIGQt4","t_start":151.9,"t_end":152.733,"duration":0.833,"spotter_score":0.93,"energy_peak":0.57},{"seg_id":"seg_0142_4591","video_id":"JzDXRkIGQt4","video_url":"https://youtu.be/JzDXRkIGQt4","t_start":153.033,"t_end":153.767,"duration":0.733,"spotter_score":0.961,"energy_peak":0.442},{"seg_id":"seg_0143_4611","video_id":"JzDXRkIGQt4","video_url":"https://youtu.be/JzDXRkIGQt4","t_start":153.7,"t_end":154.433,"duration":0.733,"spotter_score":0.801,"energy_peak":0.399},{"seg_id":"seg_0145_4642","video_id":"JzDXRkIGQt4","video_url":"https://youtu.be/JzDXRkIGQt4","t_start":154.733,"t_end":155.567,"duration":0.833,"spotter_score":0.962,"energy_peak":0.605},{"seg_id":"seg_0146_4700","video_id":"JzDXRkIGQt4","video_url":"https://youtu.be/JzDXRkIGQt4","t_start":156.667,"t_end":157.067,"duration":0.4,"spotter_score":0.966,"energy_peak":0.796},{"seg_id":"seg_0149_4757","video_id":"JzDXRkIGQt4","video_url":"https://youtu.be/JzDXRkIGQt4","t_start":158.567,"t_end":159.267,"duration":0.7,"spotter_score":0.958,"energy_peak":0.542},{"seg_id":"seg_0150_4788","video_id":"JzDXRkIGQt4","video_url":"https://youtu.be/JzDXRkIGQt4","t_start":159.6,"t_end":160.3,"duration":0.7,"spotter_score":0.965,"energy_peak":0.583},{"seg_id":"seg_0152_4802","video_id":"JzDXRkIGQt4","video_url":"https://youtu.be/JzDXRkIGQt4","t_start":160.067,"t_end":160.867,"duration":0.8,"spotter_score":0.956,"energy_peak":0.457},{"seg_id":"seg_0153_4839","video_id":"JzDXRkIGQt4","video_url":"https://youtu.be/JzDXRkIGQt4","t_start":161.3,"t_end":161.633,"duration":0.333,"spotter_score":0.977,"energy_peak":0.29},{"seg_id":"seg_0154_4878","video_id":"JzDXRkIGQt4","video_url":"https://youtu.be/JzDXRkIGQt4","t_start":162.6,"t_end":163.0,"duration":0.4,"spotter_score":0.965,"energy_peak":0.716},{"seg_id":"seg_0155_4896","video_id":"JzDXRkIGQt4","video_url":"https://youtu.be/JzDXRkIGQt4","t_start":163.2,"t_end":164.033,"duration":0.833,"spotter_score":0.726,"energy_peak":0.348},{"seg_id":"seg_0156_4925","video_id":"JzDXRkIGQt4","video_url":"https://youtu.be/JzDXRkIGQt4","t_start":164.167,"t_end":164.567,"duration":0.4,"spotter_score":0.824,"energy_peak":0.38},{"seg_id":"seg_0157_4942","video_id":"JzDXRkIGQt4","video_url":"https://youtu.be/JzDXRkIGQt4","t_start":164.733,"t_end":165.567,"duration":0.833,"spotter_score":0.753,"energy_peak":0.389},{"seg_id":"seg_0159_4976","video_id":"JzDXRkIGQt4","video_url":"https://youtu.be/JzDXRkIGQt4","t_start":165.867,"t_end":166.567,"duration":0.7,"spotter_score":0.699,"energy_peak":0.345},{"seg_id":"seg_0161_5046","video_id":"JzDXRkIGQt4","video_url":"https://youtu.be/JzDXRkIGQt4","t_start":168.2,"t_end":168.8,"duration":0.6,"spotter_score":0.856,"energy_peak":0.668},{"seg_id":"seg_0162_5092","video_id":"JzDXRkIGQt4","video_url":"https://youtu.be/JzDXRkIGQt4","t_start":169.733,"t_end":170.8,"duration":1.067,"spotter_score":0.844,"energy_peak":0.313},{"seg_id":"seg_0163_5109","video_id":"JzDXRkIGQt4","video_url":"https://youtu.be/JzDXRkIGQt4","t_start":170.3,"t_end":171.367,"duration":1.067,"spotter_score":0.837,"energy_peak":0.384},{"seg_id":"seg_0001_50","video_id":"KPyr8jFaB2k","video_url":"https://youtu.be/KPyr8jFaB2k","t_start":1.668,"t_end":2.369,"duration":0.701,"spotter_score":0.976,"energy_peak":0.615},{"seg_id":"seg_0002_71","video_id":"KPyr8jFaB2k","video_url":"https://youtu.be/KPyr8jFaB2k","t_start":2.369,"t_end":3.437,"duration":1.068,"spotter_score":0.93,"energy_peak":0.271},{"seg_id":"seg_0003_105","video_id":"KPyr8jFaB2k","video_url":"https://youtu.be/KPyr8jFaB2k","t_start":3.504,"t_end":4.204,"duration":0.701,"spotter_score":0.96,"energy_peak":0.67},{"seg_id":"seg_0004_137","video_id":"KPyr8jFaB2k","video_url":"https://youtu.be/KPyr8jFaB2k","t_start":4.571,"t_end":5.439,"duration":0.868,"spotter_score":0.935,"energy_peak":0.809},{"seg_id":"seg_0005_157","video_id":"KPyr8jFaB2k","video_url":"https://youtu.be/KPyr8jFaB2k","t_start":5.239,"t_end":5.973,"duration":0.734,"spotter_score":0.975,"energy_peak":0.912},{"seg_id":"seg_0006_183","video_id":"KPyr8jFaB2k","video_url":"https://youtu.be/KPyr8jFaB2k","t_start":6.106,"t_end":7.174,"duration":1.068,"spotter_score":0.956,"energy_peak":0.622},{"seg_id":"seg_0007_199","video_id":"KPyr8jFaB2k","video_url":"https://youtu.be/KPyr8jFaB2k","t_start":6.64,"t_end":7.708,"duration":1.068,"spotter_score":0.967,"energy_peak":0.657},{"seg_id":"seg_0008_222","video_id":"KPyr8jFaB2k","video_url":"https://youtu.be/KPyr8jFaB2k","t_start":7.407,"t_end":8.408,"duration":1.001,"spotter_score":0.95,"energy_peak":0.395},{"seg_id":"seg_0011_262","video_id":"KPyr8jFaB2k","video_url":"https://youtu.be/KPyr8jFaB2k","t_start":8.742,"t_end":9.476,"duration":0.734,"spotter_score":0.97,"energy_peak":0.467},{"seg_id":"seg_0012_290","video_id":"KPyr8jFaB2k","video_url":"https://youtu.be/KPyr8jFaB2k","t_start":9.676,"t_end":10.31,"duration":0.634,"spotter_score":0.979,"energy_peak":0.777},{"seg_id":"seg_0013_316","video_id":"KPyr8jFaB2k","video_url":"https://youtu.be/KPyr8jFaB2k","t_start":10.544,"t_end":11.378,"duration":0.834,"spotter_score":0.974,"energy_peak":0.876},{"seg_id":"seg_0014_372","video_id":"KPyr8jFaB2k","video_url":"https://youtu.be/KPyr8jFaB2k","t_start":12.412,"t_end":12.713,"duration":0.3,"spotter_score":0.946,"energy_peak":0.393},{"seg_id":"seg_0015_387","video_id":"KPyr8jFaB2k","video_url":"https://youtu.be/KPyr8jFaB2k","t_start":12.913,"t_end":13.213,"duration":0.3,"spotter_score":0.965,"energy_peak":0.411},{"seg_id":"seg_0016_401","video_id":"KPyr8jFaB2k","video_url":"https://youtu.be/KPyr8jFaB2k","t_start":13.38,"t_end":14.414,"duration":1.034,"spotter_score":0.93,"energy_peak":0.625},{"seg_id":"seg_0017_424","video_id":"KPyr8jFaB2k","video_url":"https://youtu.be/KPyr8jFaB2k","t_start":14.147,"t_end":14.915,"duration":0.767,"spotter_score":0.975,"energy_peak":0.763},{"seg_id":"seg_0018_454","video_id":"KPyr8jFaB2k","video_url":"https://youtu.be/KPyr8jFaB2k","t_start":15.148,"t_end":16.016,"duration":0.868,"spotter_score":0.975,"energy_peak":0.572},{"seg_id":"seg_0019_500","video_id":"KPyr8jFaB2k","video_url":"https://youtu.be/KPyr8jFaB2k","t_start":16.683,"t_end":17.518,"duration":0.834,"spotter_score":0.971,"energy_peak":0.807},{"seg_id":"seg_0021_538","video_id":"KPyr8jFaB2k","video_url":"https://youtu.be/KPyr8jFaB2k","t_start":17.951,"t_end":19.019,"duration":1.068,"spotter_score":0.933,"energy_peak":0.592},{"seg_id":"seg_0022_557","video_id":"KPyr8jFaB2k","video_url":"https://youtu.be/KPyr8jFaB2k","t_start":18.585,"t_end":19.653,"duration":1.068,"spotter_score":0.932,"energy_peak":0.627},{"seg_id":"seg_0024_583","video_id":"KPyr8jFaB2k","video_url":"https://youtu.be/KPyr8jFaB2k","t_start":19.453,"t_end":20.521,"duration":1.068,"spotter_score":0.941,"energy_peak":0.445},{"seg_id":"seg_0025_602","video_id":"KPyr8jFaB2k","video_url":"https://youtu.be/KPyr8jFaB2k","t_start":20.087,"t_end":21.154,"duration":1.068,"spotter_score":0.942,"energy_peak":0.424},{"seg_id":"seg_0026_638","video_id":"KPyr8jFaB2k","video_url":"https://youtu.be/KPyr8jFaB2k","t_start":21.288,"t_end":22.356,"duration":1.068,"spotter_score":0.968,"energy_peak":0.751},{"seg_id":"seg_0027_673","video_id":"KPyr8jFaB2k","video_url":"https://youtu.be/KPyr8jFaB2k","t_start":22.456,"t_end":23.524,"duration":1.068,"spotter_score":0.975,"energy_peak":0.648},{"seg_id":"seg_0028_717","video_id":"KPyr8jFaB2k","video_url":"https://youtu.be/KPyr8jFaB2k","t_start":23.924,"t_end":24.658,"duration":0.734,"spotter_score":0.971,"energy_peak":0.471},{"seg_id":"seg_0029_763","video_id":"KPyr8jFaB2k","video_url":"https://youtu.be/KPyr8jFaB2k","t_start":25.459,"t_end":25.792,"duration":0.334,"spotter_score":0.975,"energy_peak":0.6},{"seg_id":"seg_0030_776","video_id":"KPyr8jFaB2k","video_url":"https://youtu.be/KPyr8jFaB2k","t_start":25.893,"t_end":26.593,"duration":0.701,"spotter_score":0.937,"energy_peak":0.639},{"seg_id":"seg_0032_797","video_id":"KPyr8jFaB2k","video_url":"https://youtu.be/KPyr8jFaB2k","t_start":26.593,"t_end":27.661,"duration":1.068,"spotter_score":0.947,"energy_peak":0.483},{"seg_id":"seg_0034_849","video_id":"KPyr8jFaB2k","video_url":"https://youtu.be/KPyr8jFaB2k","t_start":28.328,"t_end":29.396,"duration":1.068,"spotter_score":0.97,"energy_peak":0.663},{"seg_id":"seg_0035_872","video_id":"KPyr8jFaB2k","video_url":"https://youtu.be/KPyr8jFaB2k","t_start":29.096,"t_end":30.163,"duration":1.068,"spotter_score":0.935,"energy_peak":0.469},{"seg_id":"seg_0036_962","video_id":"KPyr8jFaB2k","video_url":"https://youtu.be/KPyr8jFaB2k","t_start":32.099,"t_end":32.733,"duration":0.634,"spotter_score":0.928,"energy_peak":0.511},{"seg_id":"seg_0038_1021","video_id":"KPyr8jFaB2k","video_url":"https://youtu.be/KPyr8jFaB2k","t_start":34.067,"t_end":35.135,"duration":1.068,"spotter_score":0.936,"energy_peak":0.539},{"seg_id":"seg_0040_1068","video_id":"KPyr8jFaB2k","video_url":"https://youtu.be/KPyr8jFaB2k","t_start":35.636,"t_end":36.336,"duration":0.701,"spotter_score":0.943,"energy_peak":0.592},{"seg_id":"seg_0041_1096","video_id":"KPyr8jFaB2k","video_url":"https://youtu.be/KPyr8jFaB2k","t_start":36.57,"t_end":37.304,"duration":0.734,"spotter_score":0.971,"energy_peak":0.447},{"seg_id":"seg_0042_1129","video_id":"KPyr8jFaB2k","video_url":"https://youtu.be/KPyr8jFaB2k","t_start":37.671,"t_end":38.572,"duration":0.901,"spotter_score":0.94,"energy_peak":0.582},{"seg_id":"seg_0045_1158","video_id":"KPyr8jFaB2k","video_url":"https://youtu.be/KPyr8jFaB2k","t_start":38.639,"t_end":39.339,"duration":0.701,"spotter_score":0.974,"energy_peak":0.484},{"seg_id":"seg_0046_1196","video_id":"KPyr8jFaB2k","video_url":"https://youtu.be/KPyr8jFaB2k","t_start":39.907,"t_end":40.607,"duration":0.701,"spotter_score":0.955,"energy_peak":0.465},{"seg_id":"seg_0047_1210","video_id":"KPyr8jFaB2k","video_url":"https://youtu.be/KPyr8jFaB2k","t_start":40.374,"t_end":41.441,"duration":1.068,"spotter_score":0.906,"energy_peak":0.591},{"seg_id":"seg_0049_1239","video_id":"KPyr8jFaB2k","video_url":"https://youtu.be/KPyr8jFaB2k","t_start":41.341,"t_end":42.409,"duration":1.068,"spotter_score":0.92,"energy_peak":0.538},{"seg_id":"seg_0050_1255","video_id":"KPyr8jFaB2k","video_url":"https://youtu.be/KPyr8jFaB2k","t_start":41.875,"t_end":42.943,"duration":1.068,"spotter_score":0.945,"energy_peak":0.508},{"seg_id":"seg_0051_1297","video_id":"KPyr8jFaB2k","video_url":"https://youtu.be/KPyr8jFaB2k","t_start":43.277,"t_end":44.311,"duration":1.034,"spotter_score":0.896,"energy_peak":0.485},{"seg_id":"seg_0053_1338","video_id":"KPyr8jFaB2k","video_url":"https://youtu.be/KPyr8jFaB2k","t_start":44.645,"t_end":45.279,"duration":0.634,"spotter_score":0.969,"energy_peak":0.59},{"seg_id":"seg_0055_1365","video_id":"KPyr8jFaB2k","video_url":"https://youtu.be/KPyr8jFaB2k","t_start":45.546,"t_end":46.013,"duration":0.467,"spotter_score":0.981,"energy_peak":0.6},{"seg_id":"seg_0056_1391","video_id":"KPyr8jFaB2k","video_url":"https://youtu.be/KPyr8jFaB2k","t_start":46.413,"t_end":47.08,"duration":0.667,"spotter_score":0.941,"energy_peak":0.446},{"seg_id":"seg_0058_1423","video_id":"KPyr8jFaB2k","video_url":"https://youtu.be/KPyr8jFaB2k","t_start":47.481,"t_end":48.549,"duration":1.068,"spotter_score":0.91,"energy_peak":0.49},{"seg_id":"seg_0059_1451","video_id":"KPyr8jFaB2k","video_url":"https://youtu.be/KPyr8jFaB2k","t_start":48.415,"t_end":49.483,"duration":1.068,"spotter_score":0.965,"energy_peak":0.608},{"seg_id":"seg_0060_1484","video_id":"KPyr8jFaB2k","video_url":"https://youtu.be/KPyr8jFaB2k","t_start":49.516,"t_end":50.584,"duration":1.068,"spotter_score":0.953,"energy_peak":0.692},{"seg_id":"seg_0061_1508","video_id":"KPyr8jFaB2k","video_url":"https://youtu.be/KPyr8jFaB2k","t_start":50.317,"t_end":51.385,"duration":1.068,"spotter_score":0.964,"energy_peak":0.611},{"seg_id":"seg_0063_1559","video_id":"KPyr8jFaB2k","video_url":"https://youtu.be/KPyr8jFaB2k","t_start":52.019,"t_end":52.719,"duration":0.701,"spotter_score":0.966,"energy_peak":0.419},{"seg_id":"seg_0065_1583","video_id":"KPyr8jFaB2k","video_url":"https://youtu.be/KPyr8jFaB2k","t_start":52.819,"t_end":53.787,"duration":0.968,"spotter_score":0.943,"energy_peak":0.8},{"seg_id":"seg_0066_1617","video_id":"KPyr8jFaB2k","video_url":"https://youtu.be/KPyr8jFaB2k","t_start":53.954,"t_end":54.721,"duration":0.767,"spotter_score":0.945,"energy_peak":0.791},{"seg_id":"seg_0068_1634","video_id":"KPyr8jFaB2k","video_url":"https://youtu.be/KPyr8jFaB2k","t_start":54.521,"t_end":55.589,"duration":1.068,"spotter_score":0.923,"energy_peak":0.492},{"seg_id":"seg_0069_1653","video_id":"KPyr8jFaB2k","video_url":"https://youtu.be/KPyr8jFaB2k","t_start":55.155,"t_end":56.156,"duration":1.001,"spotter_score":0.951,"energy_peak":0.441},{"seg_id":"seg_0070_1687","video_id":"KPyr8jFaB2k","video_url":"https://youtu.be/KPyr8jFaB2k","t_start":56.29,"t_end":56.957,"duration":0.667,"spotter_score":0.976,"energy_peak":0.596},{"seg_id":"seg_0072_1720","video_id":"KPyr8jFaB2k","video_url":"https://youtu.be/KPyr8jFaB2k","t_start":57.391,"t_end":58.091,"duration":0.701,"spotter_score":0.933,"energy_peak":0.413},{"seg_id":"seg_0073_1744","video_id":"KPyr8jFaB2k","video_url":"https://youtu.be/KPyr8jFaB2k","t_start":58.191,"t_end":58.759,"duration":0.567,"spotter_score":0.907,"energy_peak":0.45},{"seg_id":"seg_0074_1765","video_id":"KPyr8jFaB2k","video_url":"https://youtu.be/KPyr8jFaB2k","t_start":58.892,"t_end":59.86,"duration":0.968,"spotter_score":0.934,"energy_peak":0.737},{"seg_id":"seg_0077_1850","video_id":"KPyr8jFaB2k","video_url":"https://youtu.be/KPyr8jFaB2k","t_start":61.728,"t_end":62.796,"duration":1.068,"spotter_score":0.963,"energy_peak":0.876},{"seg_id":"seg_0078_1880","video_id":"KPyr8jFaB2k","video_url":"https://youtu.be/KPyr8jFaB2k","t_start":62.729,"t_end":63.797,"duration":1.068,"spotter_score":0.972,"energy_peak":0.667},{"seg_id":"seg_0080_1906","video_id":"KPyr8jFaB2k","video_url":"https://youtu.be/KPyr8jFaB2k","t_start":63.597,"t_end":64.665,"duration":1.068,"spotter_score":0.944,"energy_peak":0.521},{"seg_id":"seg_0082_1937","video_id":"KPyr8jFaB2k","video_url":"https://youtu.be/KPyr8jFaB2k","t_start":64.631,"t_end":65.699,"duration":1.068,"spotter_score":0.954,"energy_peak":0.268}]